README.rst
setup.cfg
setup.py
./__init__.py
./passbook.py
./passbook.xml
./registration.xml
./tryton.cfg
./wwdr.pem
./tests/__init__.py
./tests/test_views_depends.py
./view/nereid_passbook_form.xml
./view/nereid_passbook_tree.xml
./view/registration_form.xml
./view/registration_tree.xml
fio_nereid_passbook.egg-info/PKG-INFO
fio_nereid_passbook.egg-info/SOURCES.txt
fio_nereid_passbook.egg-info/dependency_links.txt
fio_nereid_passbook.egg-info/entry_points.txt
fio_nereid_passbook.egg-info/not-zip-safe
fio_nereid_passbook.egg-info/requires.txt
fio_nereid_passbook.egg-info/top_level.txt